{
  "v8_mae": 1.5893,
  "best_params": {
    "n_estimators": 855,
    "learning_rate": 0.01465253615938746,
    "num_leaves": 285,
    "min_child_samples": 10,
    "colsample_bytree": 0.8972775451243264,
    "subsample": 0.861963986294982,
    "reg_alpha": 0.1542451379304307,
    "reg_lambda": 0.0003881756513022735,
    "min_split_gain": 0.17217230468340355,
    "max_depth": 12
  },
  "features": [
    "hour",
    "dow",
    "month",
    "is_weekend",
    "is_rush",
    "is_night",
    "hour_sin",
    "hour_cos",
    "is_weather",
    "requires_road_closure",
    "event_cause_enc",
    "zone_enc",
    "corridor_enc",
    "police_station_enc",
    "cause_x_rush",
    "cause_x_night",
    "cause_x_zone",
    "cause_x_closure",
    "is_high_priority",
    "has_description",
    "log_hawkes_zone",
    "log_hawkes_cause",
    "officer_active_load",
    "concurrent_zone_events",
    "concurrent_corridor_events",
    "corridor_stress_index",
    "live_congestion_delay_mins",
    "police_response_eta_mins",
    "road_class_score",
    "network_bottleneck_score",
    "nearby_resources_score",
    "corridor_freeflow_speed_kmh",
    "time_of_day_congestion_index",
    "congestion_x_response",
    "cause_mean",
    "cause_median",
    "cause_p90",
    "cause_p10",
    "station_mean",
    "corridor_mean",
    "corridor_cnt",
    "hour_cause_mean",
    "cause_rolling_30d",
    "station_loo",
    "corridor_loo",
    "zone_cause_loo",
    "veh_cause_loo",
    "text_svd_0",
    "text_svd_1",
    "text_svd_2",
    "text_svd_3",
    "text_svd_4",
    "text_svd_5",
    "text_svd_6",
    "text_svd_7"
  ],
  "n_features": 55
}